MANIFEST.in
README
setup.py
account/__init__.py
account/forms.py
account/models.py
account/settings.py
account/signals.py
account/tests.py
account/urls.py
account/util.py
account/views.py
account/locale/ru/LC_MESSAGES/django.mo
account/locale/ru/LC_MESSAGES/django.po
account/management/__init__.py
account/management/commands/__init__.py
account/management/commands/account_cleanup.py
account/templates/account/activation_required.html
account/templates/account/email_change.html
account/templates/account/login.html
account/templates/account/message.html
account/templates/account/password_change.html
account/templates/account/password_change_done.html
account/templates/account/password_reset.html
account/templates/account/registration.html
account/templates/account/registration_complete.html
account/templates/account/mail/activation_required_body.txt
account/templates/account/mail/activation_required_subject.txt
account/templates/account/mail/email_change_body.txt
account/templates/account/mail/email_change_subject.txt
account/templates/account/mail/password_reset_body.txt
account/templates/account/mail/password_reset_subject.txt
account/templates/account/mail/registration_complete_body.txt
account/templates/account/mail/registration_complete_subject.txt
account/templates/account/mail/welcome_body.txt
account/templates/account/mail/welcome_subject.txt
account/templatetags/__init__.py
account/templatetags/account_tags.py
django_account_modified.egg-info/PKG-INFO
django_account_modified.egg-info/SOURCES.txt
django_account_modified.egg-info/dependency_links.txt
django_account_modified.egg-info/top_level.txt