Metadata-Version: 1.0
Name: django-account-modified
Version: 0.1.8
Summary: Django application for registration and authentication, modified
Home-page: http://bitbucket.org/zeus/django-account/
Author: Pavel Zhukov
Author-email: gelios@gmail.com
License: BSD
Keywords: django application registration
Platform: UNKNOWN
Classifier: Development Status :: 4 - Beta
Classifier: Environment :: Web Environment
Classifier: Framework :: Django
Classifier: Intended Audience :: Developers
Classifier: License :: OSI Approved :: BSD License
Classifier: Operating System :: OS Independent
Classifier: Programming Language :: Python
Classifier: Topic :: Utilities
